[{"model": "pets.pet", "pk": 1, "fields": {"name": "Whiskers", "animal_type": "cat", "description": "", "listing": 3}}, {"model": "pets.pet", "pk": 2, "fields": {"name": "Fluffy", "animal_type": "cat", "description": "", "listing": 5}}, {"model": "pets.pet", "pk": 3, "fields": {"name": "Fido", "animal_type": "dog", "description": "", "listing": 5}}, {"model": "listings.listing", "pk": 1, "fields": {"first_name": "Chandler", "last_name": "Bing"}}, {"model": "listings.listing", "pk": 2, "fields": {"first_name": "Phoebe", "last_name": "Buffay"}}, {"model": "listings.listing", "pk": 3, "fields": {"first_name": "Monica", "last_name": "Geller"}}, {"model": "listings.listing", "pk": 4, "fields": {"first_name": "Ross", "last_name": "Geller"}}, {"model": "listings.listing", "pk": 5, "fields": {"first_name": "Rachel", "last_name": "Green"}}, {"model": "listings.listing", "pk": 6, "fields": {"first_name": "Joey", "last_name": "Tribbiani"}}, {"model": "listings.assignment", "pk": 1, "fields": {"start_date": "2023-01-10", "end_date": "2023-01-17", "listing": 1}}, {"model": "listings.assignment", "pk": 2, "fields": {"start_date": "2023-01-12", "end_date": "2023-01-17", "listing": 6}}, {"model": "listings.assignment", "pk": 3, "fields": {"start_date": "2023-02-12", "end_date": "2023-02-15", "listing": 2}}, {"model": "listings.assignment", "pk": 4, "fields": {"start_date": "2023-02-17", "end_date": "2023-02-20", "listing": 5}}, {"model": "listings.assignment", "pk": 5, "fields": {"start_date": "2023-07-26", "end_date": "2023-08-01", "listing": 1}}]